lazyvpn/__init__.py
lazyvpn/config.py
lazyvpn/errors.py
lazyvpn/main.py
lazyvpn/ui.py
lazyvpn-0.0.40.data/scripts/lazyvpn
lazyvpn-0.0.40.data/scripts/lazyvpn.cmd
lazyvpn-0.0.40.dist-info/METADATA
lazyvpn-0.0.40.dist-info/WHEEL
lazyvpn-0.0.40.dist-info/top_level.txt
lazyvpn-0.0.40.dist-info/RECORD
